[
  {
    "id": 1,
    "key": "Date",
    "boundingBox": {
      "id": "8afa3aaa-5b4e-41ff-9873-4d38236fa884",
      "x": 384.61967467079785,
      "y": 464.33420365535244,
      "width": 182.53137103020913,
      "height": 58.65274151436031
    },
    "hasMany": false,
    "valueBoundingBoxes": [
      {
        "id": "dd8bf300-de51-455b-b7b5-6560c4d34487",
        "x": 1188.0836560805578,
        "y": 478.9973890339425,
        "width": 598.1161890007746,
        "height": 107.53002610966057
      }
    ]
  },
  {
    "id": 2,
    "key": "Credited account",
    "boundingBox": {
      "id": "1f4c5e1a-f5c9-4968-bda8-8563224667b1",
      "x": 365.06274206041826,
      "y": 848.8355091383812,
      "width": 718.7172734314485,
      "height": 74.94516971279373
    },
    "hasMany": false,
    "valueBoundingBoxes": [
      {
        "id": "db1a967d-39f2-4ae7-b358-b85fbe137087",
        "x": 1181.5646785437646,
        "y": 860.2402088772845,
        "width": 805.0937257939582,
        "height": 112.41775456919059
      }
    ]
  },
  {
    "id": 3,
    "key": "Cash collected",
    "boundingBox": {
      "id": "b9a19226-6628-49eb-bfb1-ccc2e9739bce",
      "x": 2149.632842757552,
      "y": 1068.7832898172323,
      "width": 581.8187451587917,
      "height": 53.765013054830284
    },
    "hasMany": true,
    "valueBoundingBoxes": [
      {
        "id": "8136c454-5bb9-4ea9-9769-325d345d187f",
        "x": 2997.0999225406663,
        "y": 1036.1984334203655,
        "width": 140.15801704105345,
        "height": 61.911227154047
      },
      {
        "id": "6a8c4d51-b618-4c20-a94e-571330864e81",
        "x": 3580.5484120836563,
        "y": 1032.9399477806787,
        "width": 250.98063516653758,
        "height": 58.65274151436031
      }
    ]
  },
  {
    "id": 4,
    "key": "Charges",
    "hasMany": true,
    "valueBoundingBoxes": []
  },
  {
    "id": 5,
    "key": "Stamps",
    "hasMany": true,
    "valueBoundingBoxes": []
  },
  {
    "id": 6,
    "key": "Net in C/V",
    "hasMany": true,
    "valueBoundingBoxes": []
  },
  {
    "id": 7,
    "key": "Net credited",
    "boundingBox": {
      "id": "d1590b4e-41f9-4cde-ae69-45bb4839f76d",
      "x": 2144.7436096049573,
      "y": 1511.9373368146214,
      "width": 503.5910147172734,
      "height": 52.13577023498694
    },
    "hasMany": true,
    "valueBoundingBoxes": [
      {
        "id": "93456fca-a952-49c3-83ce-eee39a8494d5",
        "x": 3013.397366382649,
        "y": 1497.2741514360312,
        "width": 130.3795507358637,
        "height": 58.65274151436031
      },
      {
        "id": "7cd4a1aa-9cb9-465f-b905-6e2cb1c1c32d",
        "x": 3595.216111541441,
        "y": 1489.1279373368145,
        "width": 262.38884585592564,
        "height": 63.54046997389034
      }
    ]
  },
  {
    "id": 8,
    "key": "Credit value date",
    "boundingBox": {
      "id": "763fa9bc-66ab-4b46-b2a6-01a9cfd461a0",
      "x": 2146.373353989156,
      "y": 1578.7362924281983,
      "width": 720.3470178156468,
      "height": 61.911227154047
    },
    "hasMany": false,
    "valueBoundingBoxes": [
      {
        "id": "b7fe6f5f-cb90-49c6-b475-0ef1539bf733",
        "x": 3414.31448489543,
        "y": 1564.0731070496083,
        "width": 446.5499612703331,
        "height": 86.34986945169712
      }
    ]
  },
  {
    "id": 9,
    "key": "Exchange rate",
    "hasMany": false,
    "valueBoundingBoxes": []
  },
  {
    "id": 10,
    "key": "Narrative",
    "boundingBox": {
      "id": "ac3d926a-c7aa-47aa-8cd0-39cd66141bef",
      "x": 301.50271107668476,
      "y": 1888.2924281984333,
      "width": 417.21456235476376,
      "height": 66.79895561357702
    },
    "hasMany": false,
    "valueBoundingBoxes": [
      {
        "id": "8ab29a1f-879e-4763-8e71-ebafda7f8294",
        "x": 1245.124709527498,
        "y": 1891.55091383812,
        "width": 526.4074360960495,
        "height": 55.394255874673625
      }
    ]
  },
  {
    "id": 11,
    "key": "Reference",
    "boundingBox": {
      "id": "6dc8cb32-a66a-4495-886e-56ee9b3efab1",
      "x": 296.61347792408986,
      "y": 2225.5456919060052,
      "width": 412.32532920216886,
      "height": 68.42819843342036
    },
    "hasMany": false,
    "valueBoundingBoxes": [
      {
        "id": "88ec6716-d925-4e4f-8ccf-d33ef8db6486",
        "x": 852.3563129357087,
        "y": 2222.287206266318,
        "width": 1088.6692486444617,
        "height": 58.65274151436031
      }
    ]
  },
  {
    "id": 12,
    "key": "Bank",
    "boundingBox": {
      "id": "db86336d-3246-46b4-84d2-dcdd409d09eb",
      "x": 2837.3849728892333,
      "y": 2205.994778067885,
      "width": 268.90782339271885,
      "height": 60.28198433420365
    },
    "hasMany": false,
    "valueBoundingBoxes": [
      {
        "id": "7383f5e1-9cf6-4b1f-a3db-048513cb580d",
        "x": 3155.1851278079007,
        "y": 2210.882506527415,
        "width": 739.9039504260263,
        "height": 66.79895561357702
      }
    ]
  },
  {
    "id": 13,
    "key": "Branch",
    "boundingBox": {
      "id": "133d1a88-1108-4911-8ff0-6a46f6838e20",
      "x": 2843.9039504260263,
      "y": 2370.548302872063,
      "width": 260.7591014717274,
      "height": 61.911227154047
    },
    "hasMany": false,
    "valueBoundingBoxes": [
      {
        "id": "95380392-eae0-42df-b891-2a40cac5e406",
        "x": 3171.482571649884,
        "y": 2375.4360313315924,
        "width": 311.2811773818745,
        "height": 65.16971279373368
      }
    ]
  }
]